{
  "shapes": [
    {
      "line_color": null, 
      "points": [
        [
          387, 
          709
        ], 
        [
          412, 
          709
        ], 
        [
          440, 
          721
        ], 
        [
          465, 
          738
        ], 
        [
          482, 
          763
        ], 
        [
          499, 
          789
        ], 
        [
          506, 
          809
        ], 
        [
          507, 
          836
        ], 
        [
          504, 
          865
        ], 
        [
          497, 
          901
        ], 
        [
          485, 
          933
        ], 
        [
          473, 
          957
        ], 
        [
          455, 
          984
        ], 
        [
          441, 
          1002
        ], 
        [
          421, 
          1016
        ], 
        [
          389, 
          1021
        ], 
        [
          358, 
          1019
        ], 
        [
          334, 
          1009
        ], 
        [
          307, 
          992
        ], 
        [
          287, 
          973
        ], 
        [
          268, 
          945
        ], 
        [
          262, 
          907
        ], 
        [
          262, 
          870
        ], 
        [
          268, 
          833
        ], 
        [
          282, 
          796
        ], 
        [
          299, 
          765
        ], 
        [
          319, 
          741
        ], 
        [
          346, 
          723
        ]
      ], 
      "fill_color": null, 
      "label": "disc"
    }, 
    {
      "line_color": null, 
      "points": [
        [
          252, 
          699
        ], 
        [
          518, 
          699
        ], 
        [
          518, 
          1032
        ], 
        [
          252, 
          1032
        ]
      ], 
      "fill_color": null, 
      "label": "discLoc"
    }, 
    {
      "line_color": null, 
      "points": [
        [
          373.93220338983053, 
          821.4237288135594
        ], 
        [
          395.9661016949153, 
          816.3389830508474
        ], 
        [
          416.30508474576277, 
          826.5084745762713
        ], 
        [
          424.77966101694915, 
          843.4576271186442
        ], 
        [
          429.86440677966107, 
          865.4915254237288
        ], 
        [
          428.1694915254237, 
          887.5254237288136
        ], 
        [
          421.3898305084746, 
          909.5593220338983
        ], 
        [
          404.4406779661017, 
          924.8135593220339
        ], 
        [
          380.7118644067797, 
          926.5084745762713
        ], 
        [
          360.37288135593224, 
          914.6440677966102
        ], 
        [
          351.89830508474574, 
          896.0
        ], 
        [
          348.50847457627117, 
          875.6610169491526
        ], 
        [
          348.50847457627117, 
          857.0169491525425
        ], 
        [
          356.98305084745766, 
          834.9830508474577
        ]
      ], 
      "fill_color": null, 
      "label": "cup"
    }
  ], 
  "lineColor": [
    0, 
    255, 
    0, 
    128
  ], 
  "imagePath": "image_2565.jpg", 
  "flags": {}, 
  "fillColor": [
    255, 
    0, 
    0, 
    128
  ], 
  "imageData": null
}